{"users":[{"id":1,"name":"Diego Fernandes","email":"Wilson.rockeatset@gmail.com","senha":"Vai se foder2"},{"id":1,"name":"Diego Fernandes","email":"Wilson.rockeatset@gmail.com","senha":"Vai se foder2"},{"id":1,"name":"Diego Fernandes","email":"Wilson.rockeatset@gmail.com","senha":"Vai se foder2"},{"id":1,"name":"Diego Fernandes","email":"Wilson.rockeatset@gmail.com","senha":"Vai se foder2"},{"id":1,"name":"Diego Fernandes","email":"Wilson.rockeatset@gmail.com","senha":"Vai se foder2"},{"id":1,"name":"Diego Fernandes","email":"Wilson.rockeatset@gmail.com","senha":"Vai se foder2"}]}